datastudio_cli/main.py
datastudio_cli-0.2.5.dist-info/LICENSE
datastudio_cli-0.2.5.dist-info/METADATA
datastudio_cli-0.2.5.dist-info/WHEEL
datastudio_cli-0.2.5.dist-info/entry_points.txt
datastudio_cli-0.2.5.dist-info/top_level.txt
datastudio_cli-0.2.5.dist-info/RECORD
